namespace_test/stub.py
emmit_test-0.0.1.dist-info/WHEEL
emmit_test-0.0.1.dist-info/METADATA
emmit_test-0.0.1.dist-info/RECORD
