Metadata-Version: 2.1
Name: emmit-test
Version: 0.0.1
Summary: test
Classifier: Programming Language :: Python :: 2
Classifier: Programming Language :: Python :: 2.7
Classifier: Programming Language :: Python :: 3
Classifier: Programming Language :: Python :: 3.4
Classifier: Programming Language :: Python :: 3.5
Classifier: Programming Language :: Python :: 3.6
Classifier: Programming Language :: Python :: 3.7
Classifier: Programming Language :: Python :: 3.8
Classifier: Programming Language :: Python :: 3.9
Provides-Extra: dns
Provides-Extra: pandas
Requires-Dist: dnspython (==1.16); extra == "dns"
Requires-Dist: pandas (==1.0.5); extra == "pandas"
